animalid/__init__.py
animalid/probability.py
animalid/random_id.py
animalid/lists/alloys.txt
animalid/lists/animals.txt
animalid/lists/colors.txt
animalid/lists/fabrics.txt
animalid/lists/opinions.txt
animalid/lists/origins.txt
animalid/lists/shapes.txt
animalid/lists/sizes.txt
animalid-0.0.10.dist-info/LICENSE.txt
animalid-0.0.10.dist-info/METADATA
animalid-0.0.10.dist-info/WHEEL
animalid-0.0.10.dist-info/top_level.txt
animalid-0.0.10.dist-info/RECORD
