Metadata-Version: 2.1
Name: animalid
Version: 0.0.10
Summary: Library for generating unique IDs with animal names.
Home-page: https://github.com/alex-dr/animalid
Author: Alex Conway
Author-email: alex@datarobot.com
License: MIT
Keywords: random,id,unique,identifier
Platform: UNKNOWN
Classifier: Development Status :: 2 - Pre-Alpha
Classifier: Topic :: Utilities
Classifier: License :: OSI Approved :: MIT License
Classifier: Programming Language :: Python :: 2.7
Classifier: Programming Language :: Python :: 3
Provides-Extra: dev
Requires-Dist: twine ; extra == 'dev'
Requires-Dist: zest.releaser[recommended] ; extra == 'dev'
Requires-Dist: pydocstyle ; extra == 'dev'
Requires-Dist: pytest ; extra == 'dev'
Requires-Dist: pytest-flake8 ; extra == 'dev'
Requires-Dist: pytest-pep8 ; extra == 'dev'
Requires-Dist: pytest-mccabe ; extra == 'dev'
Requires-Dist: pytest-cov ; extra == 'dev'
Provides-Extra: release
Requires-Dist: twine ; extra == 'release'
Requires-Dist: zest.releaser[recommended] ; extra == 'release'
Provides-Extra: testing
Requires-Dist: pydocstyle ; extra == 'testing'
Requires-Dist: pytest ; extra == 'testing'
Requires-Dist: pytest-flake8 ; extra == 'testing'
Requires-Dist: pytest-pep8 ; extra == 'testing'
Requires-Dist: pytest-mccabe ; extra == 'testing'
Requires-Dist: pytest-cov ; extra == 'testing'
